tictactoecli/__init__.py
tictactoecli/board.py
tictactoecli/mark.py
tictaccli-1.0.0.1.dist-info/LICENSE
tictaccli-1.0.0.1.dist-info/METADATA
tictaccli-1.0.0.1.dist-info/WHEEL
tictaccli-1.0.0.1.dist-info/entry_points.txt
tictaccli-1.0.0.1.dist-info/top_level.txt
tictaccli-1.0.0.1.dist-info/RECORD
