Metadata-Version: 2.1
Name: tictaccli
Version: 1.0.0.1
Summary: A simple Tic-Tac-Toe game in command-line.
Home-page: https://github.com/erenoguzyesil/tictactoecli
License: MIT
Keywords: cli game tictactoe commandline
License-File: LICENSE
